cheesebread/__init__.py
cheesebread/config.py
cheesebread/datasets/__init__.py
cheesebread/datasets/viafoura.py
cheesebread/helpers/__init__.py
cheesebread/helpers/aws.py
cheesebread/helpers/requests.py
cheesebread/wrappers/__init__.py
cheesebread/wrappers/viafoura.py
cheesebread-0.0.2.dist-info/LICENSE
cheesebread-0.0.2.dist-info/METADATA
cheesebread-0.0.2.dist-info/WHEEL
cheesebread-0.0.2.dist-info/top_level.txt
cheesebread-0.0.2.dist-info/RECORD
