Metadata-Version: 2.1
Name: cheesebread
Version: 0.0.2
Summary: cheesebread: a toolbox for data science
Home-page: https://github.com/g4brielvs/cheesebread
Author: g4brielvs
Author-email: g4brielvs@g4brievs.me
License: GPLv3+
Keywords: toolbox,data science
Platform: UNKNOWN
Classifier: Development Status :: 4 - Beta
Classifier: Intended Audience :: Science/Research
Classifier: License :: OSI Approved :: GNU General Public License v3 or later (GPLv3+)
Classifier: Programming Language :: Python :: 3.7
Classifier: Programming Language :: Python :: 3.8
Classifier: Topic :: Utilities
Requires-Python: >=3.7
Requires-Dist: aiofiles
Requires-Dist: aiohttp
Requires-Dist: boto3
Requires-Dist: pandas (>=0.24)
Requires-Dist: requests
Requires-Dist: riprova
Requires-Dist: tqdm
